spaFR/FR.py
spaFR/__init__.py
spaFR/del_clustering.py
spaFR/del_metacell_utils.py
spaFR/del_se_utils.py
spaFR/del_tree_utils.py
spaFR/evaluation.py
spaFR/nestedness_calculator.py
spaFR/plotting.py
spaFR/run_FR_SC.py
spaFR/run_FR_ST.py
spaFR/utils.py
spafr-0.0.3.dist-info/licenses/LICENSE
spafr-0.0.3.dist-info/METADATA
spafr-0.0.3.dist-info/WHEEL
spafr-0.0.3.dist-info/top_level.txt
spafr-0.0.3.dist-info/RECORD
