Metadata-Version: 2.4
Name: spaFR
Version: 0.0.3
Summary: Deciphering cellular resolution functional redundancy from transcriptomic data
Home-page: https://github.com/wangjingwan/SpaFR/tree/master#
Author: Jingwan WANG
Author-email: wanwang6-c@my.cityu.edu.hk
License: MIT
License-File: LICENSE
Requires-Dist: pandas==1.5.3
Requires-Dist: numpy==1.24.4
Requires-Dist: seaborn==0.11.2
Requires-Dist: matplotlib==3.8.4
Requires-Dist: tqdm==4.67.1
Requires-Dist: statannot==0.2.3
Requires-Dist: scipy==1.9.3
Requires-Dist: networkx==3.2.1
Requires-Dist: statsmodels==0.14.5
Requires-Dist: scikit-learn==1.6.1
Dynamic: author
Dynamic: author-email
Dynamic: home-page
Dynamic: license
Dynamic: license-file
Dynamic: requires-dist
Dynamic: summary
